{
  "instance_name": "ftv47_p5_f70_lL",

  "schedule": 
  [
  {
    "route": 1,
    "tasks": 
    [
      { "customer":   0, "arrival_starting": [   0.0,    0.0] },
      { "customer":  25, "arrival_starting": [  20.0,   39.0] },
      { "customer":   1, "arrival_starting": [  58.0,   58.0] },
      { "customer":  33, "arrival_starting": [ 114.0,  114.0] },
      { "customer":   2, "arrival_starting": [ 202.0,  202.0] },
      { "customer":  41, "arrival_starting": [ 272.0,  272.0] },
      { "customer":  43, "arrival_starting": [ 304.0,  304.0] },
      { "customer":  22, "arrival_starting": [ 333.0,  333.0] },
      { "customer":  37, "arrival_starting": [ 443.0,  443.0] },
      { "customer":  17, "arrival_starting": [ 495.0,  495.0] },
      { "customer":  12, "arrival_starting": [ 540.0,  540.0] },
      { "customer":   7, "arrival_starting": [ 600.0,  600.0] },
      { "customer":  23, "arrival_starting": [ 713.0,  713.0] },
      { "customer":  34, "arrival_starting": [ 747.0,  747.0] },
      { "customer":  46, "arrival_starting": [ 777.0,  777.0] },
      { "customer":  36, "arrival_starting": [ 789.0,  789.0] },
      { "customer":  14, "arrival_starting": [ 823.0,  823.0] },
      { "customer":  15, "arrival_starting": [ 869.0,  869.0] },
      { "customer":  16, "arrival_starting": [ 905.0,  905.0] },
      { "customer":  45, "arrival_starting": [ 927.0,  927.0] },
      { "customer":  39, "arrival_starting": [ 989.0,  994.0] },
      { "customer":  19, "arrival_starting": [1035.0, 1035.0] },
      { "customer":  44, "arrival_starting": [1051.0, 1051.0] },
      { "customer":  21, "arrival_starting": [1163.0, 1163.0] },
      { "customer":  40, "arrival_starting": [1197.0, 1197.0] },
      { "customer":  47, "arrival_starting": [1211.0, 1211.0] },
      { "customer":  26, "arrival_starting": [1219.0, 1219.0] },
      { "customer":  42, "arrival_starting": [1258.0, 1258.0] },
      { "customer":   3, "arrival_starting": [1347.0, 1347.0] },
      { "customer":  24, "arrival_starting": [1373.0, 1373.0] },
      { "customer":   4, "arrival_starting": [1380.0, 1380.0] },
      { "customer":  29, "arrival_starting": [1401.0, 1401.0] },
      { "customer":  30, "arrival_starting": [1445.0, 1445.0] },
      { "customer":   5, "arrival_starting": [1456.0, 1456.0] },
      { "customer":   6, "arrival_starting": [1493.0, 1493.0] },
      { "customer":  10, "arrival_starting": [1522.0, 1522.0] },
      { "customer":  11, "arrival_starting": [1554.0, 1554.0] },
      { "customer":   0, "arrival_starting": [1602.0, 1602.0] }
    ]
  },
  {
    "route": 2,
    "tasks": 
    [
      { "customer":   0, "arrival_starting": [   0.0,    0.0] },
      { "customer":  25, "arrival_starting": [  20.0,   39.0] },
      { "customer":   1, "arrival_starting": [  58.0,   58.0] },
      { "customer":   9, "arrival_starting": [  95.0,   95.0] },
      { "customer":  33, "arrival_starting": [ 114.0,  114.0] },
      { "customer":   2, "arrival_starting": [ 202.0,  202.0] },
      { "customer":  41, "arrival_starting": [ 272.0,  272.0] },
      { "customer":  20, "arrival_starting": [ 389.0,  389.0] },
      { "customer":  37, "arrival_starting": [ 443.0,  443.0] },
      { "customer":  18, "arrival_starting": [ 475.0,  475.0] },
      { "customer":   7, "arrival_starting": [ 600.0,  600.0] },
      { "customer":  23, "arrival_starting": [ 713.0,  713.0] },
      { "customer":  46, "arrival_starting": [ 775.0,  775.0] },
      { "customer":  36, "arrival_starting": [ 787.0,  787.0] },
      { "customer":  35, "arrival_starting": [ 870.0,  870.0] },
      { "customer":  14, "arrival_starting": [ 880.0,  880.0] },
      { "customer":  45, "arrival_starting": [ 933.0,  933.0] },
      { "customer":  44, "arrival_starting": [1045.0, 1045.0] },
      { "customer":  19, "arrival_starting": [1115.0, 1115.0] },
      { "customer":  39, "arrival_starting": [1145.0, 1145.0] },
      { "customer":  40, "arrival_starting": [1186.0, 1186.0] },
      { "customer":  47, "arrival_starting": [1200.0, 1200.0] },
      { "customer":  26, "arrival_starting": [1208.0, 1208.0] },
      { "customer":  42, "arrival_starting": [1247.0, 1247.0] },
      { "customer":  28, "arrival_starting": [1274.0, 1274.0] },
      { "customer":   3, "arrival_starting": [1336.0, 1336.0] },
      { "customer":   4, "arrival_starting": [1356.0, 1356.0] },
      { "customer":  29, "arrival_starting": [1377.0, 1377.0] },
      { "customer":  30, "arrival_starting": [1421.0, 1421.0] },
      { "customer":  31, "arrival_starting": [1473.0, 1473.0] },
      { "customer":   8, "arrival_starting": [1561.0, 1561.0] },
      { "customer":  11, "arrival_starting": [1592.0, 1592.0] },
      { "customer":  10, "arrival_starting": [1624.0, 1624.0] },
      { "customer":   0, "arrival_starting": [1663.0, 1663.0] }
    ]
  },
  {
    "route": 3,
    "tasks": 
    [
      { "customer":   0, "arrival_starting": [   0.0,    0.0] },
      { "customer":   1, "arrival_starting": [  39.0,   39.0] },
      { "customer":   9, "arrival_starting": [  76.0,   76.0] },
      { "customer":  33, "arrival_starting": [  95.0,   95.0] },
      { "customer":  27, "arrival_starting": [ 126.0,  126.0] },
      { "customer":   2, "arrival_starting": [ 211.0,  211.0] },
      { "customer":  43, "arrival_starting": [ 283.0,  283.0] },
      { "customer":  22, "arrival_starting": [ 312.0,  312.0] },
      { "customer":  20, "arrival_starting": [ 368.0,  368.0] },
      { "customer":  18, "arrival_starting": [ 412.0,  412.0] },
      { "customer":  17, "arrival_starting": [ 432.0,  432.0] },
      { "customer":  12, "arrival_starting": [ 477.0,  477.0] },
      { "customer":  32, "arrival_starting": [ 496.0,  496.0] },
      { "customer":   7, "arrival_starting": [ 563.0,  563.0] },
      { "customer":  13, "arrival_starting": [ 719.0,  719.0] },
      { "customer":  46, "arrival_starting": [ 737.0,  737.0] },
      { "customer":  35, "arrival_starting": [ 832.0,  939.0] },
      { "customer":  15, "arrival_starting": [ 995.0,  995.0] },
      { "customer":  44, "arrival_starting": [1120.0, 1120.0] },
      { "customer":  19, "arrival_starting": [1190.0, 1190.0] },
      { "customer":  40, "arrival_starting": [1261.0, 1320.0] },
      { "customer":  47, "arrival_starting": [1334.0, 1334.0] },
      { "customer":  26, "arrival_starting": [1342.0, 1342.0] },
      { "customer":  42, "arrival_starting": [1381.0, 1381.0] },
      { "customer":  28, "arrival_starting": [1408.0, 1408.0] },
      { "customer":   3, "arrival_starting": [1470.0, 1470.0] },
      { "customer":  29, "arrival_starting": [1511.0, 1511.0] },
      { "customer":  30, "arrival_starting": [1555.0, 1555.0] },
      { "customer":   6, "arrival_starting": [1603.0, 1603.0] },
      { "customer":   8, "arrival_starting": [1633.0, 1633.0] },
      { "customer":  11, "arrival_starting": [1664.0, 1664.0] },
      { "customer":   0, "arrival_starting": [1712.0, 1712.0] }
    ]
  },
  {
    "route": 4,
    "tasks": 
    [
      { "customer":   0, "arrival_starting": [   0.0,    0.0] },
      { "customer":  25, "arrival_starting": [  20.0,   39.0] },
      { "customer":   9, "arrival_starting": [  95.0,   95.0] },
      { "customer":   2, "arrival_starting": [ 202.0,  202.0] },
      { "customer":  43, "arrival_starting": [ 274.0,  274.0] },
      { "customer":  20, "arrival_starting": [ 359.0,  359.0] },
      { "customer":  37, "arrival_starting": [ 413.0,  413.0] },
      { "customer":  18, "arrival_starting": [ 445.0,  445.0] },
      { "customer":  17, "arrival_starting": [ 465.0,  465.0] },
      { "customer":  12, "arrival_starting": [ 510.0,  510.0] },
      { "customer":  32, "arrival_starting": [ 529.0,  529.0] },
      { "customer":   7, "arrival_starting": [ 596.0,  596.0] },
      { "customer":  34, "arrival_starting": [ 743.0,  743.0] },
      { "customer":  13, "arrival_starting": [ 755.0,  755.0] },
      { "customer":  46, "arrival_starting": [ 773.0,  773.0] },
      { "customer":  36, "arrival_starting": [ 785.0,  785.0] },
      { "customer":  35, "arrival_starting": [ 868.0,  868.0] },
      { "customer":  15, "arrival_starting": [ 924.0,  924.0] },
      { "customer":  44, "arrival_starting": [1049.0, 1049.0] },
      { "customer":  19, "arrival_starting": [1119.0, 1119.0] },
      { "customer":  39, "arrival_starting": [1149.0, 1149.0] },
      { "customer":  40, "arrival_starting": [1190.0, 1190.0] },
      { "customer":  26, "arrival_starting": [1212.0, 1212.0] },
      { "customer":   3, "arrival_starting": [1329.0, 1329.0] },
      { "customer":  24, "arrival_starting": [1355.0, 1355.0] },
      { "customer":   4, "arrival_starting": [1362.0, 1362.0] },
      { "customer":  29, "arrival_starting": [1383.0, 1383.0] },
      { "customer":  30, "arrival_starting": [1427.0, 1427.0] },
      { "customer":   6, "arrival_starting": [1475.0, 1475.0] },
      { "customer":   8, "arrival_starting": [1505.0, 1505.0] },
      { "customer":  11, "arrival_starting": [1536.0, 1536.0] },
      { "customer":  10, "arrival_starting": [1568.0, 1568.0] },
      { "customer":   0, "arrival_starting": [1607.0, 1607.0] }
    ]
  },
  {
    "route": 5,
    "tasks": 
    [
      { "customer":   0, "arrival_starting": [   0.0,    0.0] },
      { "customer":  25, "arrival_starting": [  20.0,   39.0] },
      { "customer":   1, "arrival_starting": [  58.0,   58.0] },
      { "customer":   9, "arrival_starting": [  95.0,   95.0] },
      { "customer":  33, "arrival_starting": [ 114.0,  114.0] },
      { "customer":  27, "arrival_starting": [ 145.0,  145.0] },
      { "customer":   2, "arrival_starting": [ 230.0,  230.0] },
      { "customer":  41, "arrival_starting": [ 300.0,  300.0] },
      { "customer":  43, "arrival_starting": [ 332.0,  332.0] },
      { "customer":  22, "arrival_starting": [ 361.0,  361.0] },
      { "customer":  20, "arrival_starting": [ 417.0,  417.0] },
      { "customer":  38, "arrival_starting": [ 436.0,  436.0] },
      { "customer":  18, "arrival_starting": [ 461.0,  461.0] },
      { "customer":  12, "arrival_starting": [ 526.0,  526.0] },
      { "customer":  32, "arrival_starting": [ 545.0,  545.0] },
      { "customer":   7, "arrival_starting": [ 612.0,  612.0] },
      { "customer":  23, "arrival_starting": [ 725.0,  725.0] },
      { "customer":  34, "arrival_starting": [ 759.0,  759.0] },
      { "customer":  13, "arrival_starting": [ 771.0,  771.0] },
      { "customer":  36, "arrival_starting": [ 801.0,  801.0] },
      { "customer":  35, "arrival_starting": [ 884.0,  884.0] },
      { "customer":  14, "arrival_starting": [ 894.0,  894.0] },
      { "customer":  15, "arrival_starting": [ 940.0,  940.0] },
      { "customer":  39, "arrival_starting": [1060.0, 1060.0] },
      { "customer":  21, "arrival_starting": [1086.0, 1086.0] },
      { "customer":  40, "arrival_starting": [1120.0, 1165.0] },
      { "customer":  47, "arrival_starting": [1179.0, 1179.0] },
      { "customer":  42, "arrival_starting": [1226.0, 1226.0] },
      { "customer":  28, "arrival_starting": [1253.0, 1253.0] },
      { "customer":   3, "arrival_starting": [1315.0, 1315.0] },
      { "customer":  24, "arrival_starting": [1341.0, 1341.0] },
      { "customer":   4, "arrival_starting": [1348.0, 1348.0] },
      { "customer":  29, "arrival_starting": [1369.0, 1369.0] },
      { "customer":  30, "arrival_starting": [1413.0, 1413.0] },
      { "customer":  31, "arrival_starting": [1465.0, 1465.0] },
      { "customer":  11, "arrival_starting": [1584.0, 1584.0] },
      { "customer":   0, "arrival_starting": [1632.0, 1632.0] }
    ]
  }
  ]

}

