{
  "instance_name": "kroA100_p5_f70_lH",

  "schedule": 
  [
  {
    "route": 1,
    "tasks": 
    [
      { "customer":   0, "arrival_starting": [   0.0,    0.0] },
      { "customer":  62, "arrival_starting": [ 288.0,  288.0] },
      { "customer":   5, "arrival_starting": [ 445.0,  445.0] },
      { "customer":  48, "arrival_starting": [ 492.0,  492.0] },
      { "customer":  89, "arrival_starting": [ 700.0,  700.0] },
      { "customer":  18, "arrival_starting": [1076.0, 1076.0] },
      { "customer":  74, "arrival_starting": [1310.0, 1310.0] },
      { "customer":  91, "arrival_starting": [1668.0, 1668.0] },
      { "customer":   7, "arrival_starting": [1874.0, 1874.0] },
      { "customer":  41, "arrival_starting": [2122.0, 2122.0] },
      { "customer":  88, "arrival_starting": [2302.0, 2302.0] },
      { "customer":  30, "arrival_starting": [2490.0, 2490.0] },
      { "customer":  55, "arrival_starting": [2857.0, 2857.0] },
      { "customer":  96, "arrival_starting": [3073.0, 3073.0] },
      { "customer":   3, "arrival_starting": [3397.0, 3397.0] },
      { "customer":  64, "arrival_starting": [3544.0, 3544.0] },
      { "customer":  25, "arrival_starting": [3827.0, 3827.0] },
      { "customer":  65, "arrival_starting": [4150.0, 4150.0] },
      { "customer":  69, "arrival_starting": [4550.0, 4550.0] },
      { "customer":  93, "arrival_starting": [4863.0, 4863.0] },
      { "customer":  15, "arrival_starting": [5024.0, 5024.0] },
      { "customer":  87, "arrival_starting": [5082.0, 6946.0] },
      { "customer":  52, "arrival_starting": [7176.0, 7176.0] },
      { "customer":  78, "arrival_starting": [7399.0, 7399.0] },
      { "customer":  17, "arrival_starting": [7629.0, 7629.0] },
      { "customer":  23, "arrival_starting": [7810.0, 7810.0] },
      { "customer":  37, "arrival_starting": [7906.0, 7906.0] },
      { "customer":  98, "arrival_starting": [8219.0, 8219.0] },
      { "customer":  35, "arrival_starting": [8519.0, 8519.0] },
      { "customer":   9, "arrival_starting": [8960.0, 8960.0] },
      { "customer":  20, "arrival_starting": [9380.0, 9380.0] },
      { "customer":  14, "arrival_starting": [9782.0, 9782.0] },
      { "customer":  10, "arrival_starting": [9895.0, 9895.0] },
      { "customer":  31, "arrival_starting": [10097.0, 10097.0] },
      { "customer":  90, "arrival_starting": [10312.0, 10312.0] },
      { "customer":  97, "arrival_starting": [10411.0, 10411.0] },
      { "customer":  22, "arrival_starting": [10519.0, 10519.0] },
      { "customer":  76, "arrival_starting": [10901.0, 10901.0] },
      { "customer":  59, "arrival_starting": [11092.0, 11092.0] },
      { "customer":  61, "arrival_starting": [11243.0, 11243.0] },
      { "customer":  85, "arrival_starting": [11551.0, 11551.0] },
      { "customer":  26, "arrival_starting": [11632.0, 11632.0] },
      { "customer":  11, "arrival_starting": [11768.0, 11768.0] },
      { "customer":  19, "arrival_starting": [11922.0, 11922.0] },
      { "customer":  56, "arrival_starting": [12126.0, 12126.0] },
      { "customer":   8, "arrival_starting": [12226.0, 12226.0] },
      { "customer":  54, "arrival_starting": [12524.0, 12524.0] },
      { "customer":  82, "arrival_starting": [12547.0, 12547.0] },
      { "customer":  33, "arrival_starting": [12693.0, 12693.0] },
      { "customer":  28, "arrival_starting": [12994.0, 12994.0] },
      { "customer":  45, "arrival_starting": [13142.0, 13142.0] },
      { "customer":  42, "arrival_starting": [13340.0, 13340.0] },
      { "customer":   2, "arrival_starting": [13511.0, 13511.0] },
      { "customer":  40, "arrival_starting": [13962.0, 13962.0] },
      { "customer":  70, "arrival_starting": [14045.0, 14045.0] },
      { "customer":  99, "arrival_starting": [14166.0, 14166.0] },
      { "customer":  47, "arrival_starting": [14418.0, 14418.0] },
      { "customer":  29, "arrival_starting": [14845.0, 14845.0] },
      { "customer":  51, "arrival_starting": [15214.0, 15214.0] },
      { "customer":  77, "arrival_starting": [15254.0, 15254.0] },
      { "customer":  36, "arrival_starting": [15560.0, 15560.0] },
      { "customer":  12, "arrival_starting": [15993.0, 15993.0] },
      { "customer":  75, "arrival_starting": [16096.0, 16096.0] },
      { "customer":  94, "arrival_starting": [16356.0, 16356.0] },
      { "customer":  84, "arrival_starting": [17349.0, 17349.0] },
      { "customer":  67, "arrival_starting": [17502.0, 17502.0] },
      { "customer":  43, "arrival_starting": [17960.0, 17960.0] },
      { "customer":  39, "arrival_starting": [18367.0, 18367.0] },
      { "customer":  63, "arrival_starting": [18447.0, 18447.0] },
      { "customer":  68, "arrival_starting": [18744.0, 18744.0] },
      { "customer":  80, "arrival_starting": [19047.0, 19047.0] },
      { "customer":  24, "arrival_starting": [19098.0, 19098.0] },
      { "customer":  86, "arrival_starting": [19438.0, 19438.0] },
      { "customer":  50, "arrival_starting": [19584.0, 19584.0] },
      { "customer":  92, "arrival_starting": [20300.0, 20300.0] },
      { "customer":  27, "arrival_starting": [20348.0, 20348.0] },
      { "customer":   0, "arrival_starting": [20764.0, 20764.0] }
    ]
  },
  {
    "route": 2,
    "tasks": 
    [
      { "customer":   0, "arrival_starting": [   0.0,    0.0] },
      { "customer":  62, "arrival_starting": [ 288.0,  288.0] },
      { "customer":   5, "arrival_starting": [ 445.0,  445.0] },
      { "customer":  48, "arrival_starting": [ 492.0,  492.0] },
      { "customer":  89, "arrival_starting": [ 700.0,  700.0] },
      { "customer":  41, "arrival_starting": [1645.0, 1645.0] },
      { "customer":  30, "arrival_starting": [1874.0, 1874.0] },
      { "customer":  79, "arrival_starting": [1961.0, 1961.0] },
      { "customer":  96, "arrival_starting": [2458.0, 2458.0] },
      { "customer":  64, "arrival_starting": [2925.0, 2925.0] },
      { "customer":  25, "arrival_starting": [3208.0, 3208.0] },
      { "customer":  65, "arrival_starting": [3531.0, 3531.0] },
      { "customer":  69, "arrival_starting": [3931.0, 3931.0] },
      { "customer":  21, "arrival_starting": [4117.0, 4117.0] },
      { "customer":  93, "arrival_starting": [4251.0, 4251.0] },
      { "customer":  15, "arrival_starting": [4412.0, 4412.0] },
      { "customer":  87, "arrival_starting": [4470.0, 4470.0] },
      { "customer":  52, "arrival_starting": [4700.0, 4700.0] },
      { "customer":  78, "arrival_starting": [4923.0, 4923.0] },
      { "customer":  17, "arrival_starting": [5153.0, 5153.0] },
      { "customer":  37, "arrival_starting": [5430.0, 5430.0] },
      { "customer":  35, "arrival_starting": [5658.0, 5658.0] },
      { "customer":   9, "arrival_starting": [6099.0, 6099.0] },
      { "customer":  20, "arrival_starting": [6519.0, 6519.0] },
      { "customer":  73, "arrival_starting": [6585.0, 6585.0] },
      { "customer":  58, "arrival_starting": [6674.0, 6674.0] },
      { "customer":  16, "arrival_starting": [7032.0, 7032.0] },
      { "customer":  10, "arrival_starting": [7147.0, 7147.0] },
      { "customer":  31, "arrival_starting": [7349.0, 7349.0] },
      { "customer":  44, "arrival_starting": [7571.0, 7571.0] },
      { "customer":  59, "arrival_starting": [8090.0, 8090.0] },
      { "customer":  76, "arrival_starting": [8281.0, 8281.0] },
      { "customer":  61, "arrival_starting": [8502.0, 8502.0] },
      { "customer":  85, "arrival_starting": [8810.0, 8810.0] },
      { "customer":  26, "arrival_starting": [8891.0, 8891.0] },
      { "customer":  11, "arrival_starting": [9027.0, 9027.0] },
      { "customer":  19, "arrival_starting": [9181.0, 9181.0] },
      { "customer":  56, "arrival_starting": [9385.0, 9385.0] },
      { "customer":   8, "arrival_starting": [9485.0, 9485.0] },
      { "customer":   6, "arrival_starting": [9535.0, 9535.0] },
      { "customer":  82, "arrival_starting": [9805.0, 9805.0] },
      { "customer":  33, "arrival_starting": [9951.0, 9951.0] },
      { "customer":  28, "arrival_starting": [10252.0, 10252.0] },
      { "customer":  45, "arrival_starting": [10400.0, 10400.0] },
      { "customer":  42, "arrival_starting": [10598.0, 13592.0] },
      { "customer":   2, "arrival_starting": [13763.0, 13763.0] },
      { "customer":  13, "arrival_starting": [13984.0, 13984.0] },
      { "customer":  70, "arrival_starting": [14252.0, 14252.0] },
      { "customer":  47, "arrival_starting": [14609.0, 14609.0] },
      { "customer":  51, "arrival_starting": [15005.0, 15005.0] },
      { "customer":  95, "arrival_starting": [15111.0, 15111.0] },
      { "customer":  38, "arrival_starting": [15395.0, 15395.0] },
      { "customer":  36, "arrival_starting": [15849.0, 15849.0] },
      { "customer":  32, "arrival_starting": [16257.0, 16257.0] },
      { "customer":  94, "arrival_starting": [16568.0, 16568.0] },
      { "customer":  81, "arrival_starting": [16813.0, 16813.0] },
      { "customer":   1, "arrival_starting": [17383.0, 17383.0] },
      { "customer":  43, "arrival_starting": [17640.0, 17640.0] },
      { "customer":  68, "arrival_starting": [18088.0, 18088.0] },
      { "customer":  80, "arrival_starting": [18391.0, 18391.0] },
      { "customer":  24, "arrival_starting": [18442.0, 18442.0] },
      { "customer":  50, "arrival_starting": [18696.0, 18696.0] },
      { "customer":  57, "arrival_starting": [19131.0, 19131.0] },
      { "customer":  66, "arrival_starting": [19476.0, 19476.0] },
      { "customer":  46, "arrival_starting": [20335.0, 20335.0] },
      { "customer":   0, "arrival_starting": [20764.0, 20764.0] }
    ]
  },
  {
    "route": 3,
    "tasks": 
    [
      { "customer":   0, "arrival_starting": [   0.0,    0.0] },
      { "customer":  62, "arrival_starting": [ 288.0,  288.0] },
      { "customer":  89, "arrival_starting": [ 662.0,  662.0] },
      { "customer":  18, "arrival_starting": [1038.0, 1038.0] },
      { "customer":   7, "arrival_starting": [1729.0, 1729.0] },
      { "customer":  41, "arrival_starting": [1977.0, 1977.0] },
      { "customer":  30, "arrival_starting": [2206.0, 2206.0] },
      { "customer":  55, "arrival_starting": [2573.0, 2573.0] },
      { "customer":  96, "arrival_starting": [2789.0, 2789.0] },
      { "customer":   3, "arrival_starting": [3113.0, 3113.0] },
      { "customer":  25, "arrival_starting": [3530.0, 3530.0] },
      { "customer":  65, "arrival_starting": [3853.0, 3853.0] },
      { "customer":  69, "arrival_starting": [4253.0, 4253.0] },
      { "customer":  21, "arrival_starting": [4439.0, 4439.0] },
      { "customer":  93, "arrival_starting": [4573.0, 4573.0] },
      { "customer":  15, "arrival_starting": [4734.0, 4734.0] },
      { "customer":  87, "arrival_starting": [4792.0, 4792.0] },
      { "customer":  52, "arrival_starting": [5022.0, 5022.0] },
      { "customer":  78, "arrival_starting": [5245.0, 5245.0] },
      { "customer":  17, "arrival_starting": [5475.0, 5475.0] },
      { "customer":  23, "arrival_starting": [5656.0, 5656.0] },
      { "customer":  83, "arrival_starting": [5995.0, 5995.0] },
      { "customer":   9, "arrival_starting": [6135.0, 6135.0] },
      { "customer":  20, "arrival_starting": [6555.0, 6555.0] },
      { "customer":  58, "arrival_starting": [6706.0, 6706.0] },
      { "customer":  10, "arrival_starting": [7067.0, 7067.0] },
      { "customer":  31, "arrival_starting": [7269.0, 7269.0] },
      { "customer":  22, "arrival_starting": [7652.0, 7652.0] },
      { "customer":  61, "arrival_starting": [8145.0, 8145.0] },
      { "customer":  34, "arrival_starting": [8470.0, 8470.0] },
      { "customer":  85, "arrival_starting": [8611.0, 11155.0] },
      { "customer":  26, "arrival_starting": [11236.0, 11236.0] },
      { "customer":  19, "arrival_starting": [11417.0, 11417.0] },
      { "customer":  56, "arrival_starting": [11621.0, 11621.0] },
      { "customer":   6, "arrival_starting": [11714.0, 11714.0] },
      { "customer":  54, "arrival_starting": [11978.0, 11978.0] },
      { "customer":  33, "arrival_starting": [12147.0, 12147.0] },
      { "customer":  45, "arrival_starting": [12458.0, 12458.0] },
      { "customer":  42, "arrival_starting": [12656.0, 12656.0] },
      { "customer":   2, "arrival_starting": [12827.0, 12827.0] },
      { "customer":  70, "arrival_starting": [13228.0, 13228.0] },
      { "customer":  99, "arrival_starting": [13349.0, 13349.0] },
      { "customer":  13, "arrival_starting": [13617.0, 13617.0] },
      { "customer":  84, "arrival_starting": [14480.0, 14480.0] },
      { "customer":  38, "arrival_starting": [14852.0, 14852.0] },
      { "customer":  95, "arrival_starting": [15136.0, 15136.0] },
      { "customer":  77, "arrival_starting": [15204.0, 15204.0] },
      { "customer":  51, "arrival_starting": [15244.0, 15244.0] },
      { "customer":   4, "arrival_starting": [15503.0, 15503.0] },
      { "customer":  36, "arrival_starting": [15572.0, 15572.0] },
      { "customer":  32, "arrival_starting": [15980.0, 15980.0] },
      { "customer":  75, "arrival_starting": [16072.0, 16072.0] },
      { "customer":  94, "arrival_starting": [16332.0, 16332.0] },
      { "customer":   1, "arrival_starting": [17126.0, 17126.0] },
      { "customer":  39, "arrival_starting": [17463.0, 17463.0] },
      { "customer":  63, "arrival_starting": [17543.0, 17543.0] },
      { "customer":  80, "arrival_starting": [18142.0, 18142.0] },
      { "customer":  86, "arrival_starting": [18527.0, 18527.0] },
      { "customer":  50, "arrival_starting": [18673.0, 18673.0] },
      { "customer":  57, "arrival_starting": [19108.0, 19108.0] },
      { "customer":  66, "arrival_starting": [19453.0, 19453.0] },
      { "customer":  27, "arrival_starting": [19754.0, 19754.0] },
      { "customer":  92, "arrival_starting": [19802.0, 19802.0] },
      { "customer":  46, "arrival_starting": [20335.0, 20335.0] },
      { "customer":   0, "arrival_starting": [20764.0, 20764.0] }
    ]
  },
  {
    "route": 4,
    "tasks": 
    [
      { "customer":   0, "arrival_starting": [   0.0,    0.0] },
      { "customer":  62, "arrival_starting": [ 288.0,  288.0] },
      { "customer":  89, "arrival_starting": [ 662.0,  662.0] },
      { "customer":  18, "arrival_starting": [1038.0, 1038.0] },
      { "customer":  74, "arrival_starting": [1272.0, 1272.0] },
      { "customer":  91, "arrival_starting": [1630.0, 1630.0] },
      { "customer":   7, "arrival_starting": [1836.0, 1836.0] },
      { "customer":  41, "arrival_starting": [2084.0, 2084.0] },
      { "customer":  30, "arrival_starting": [2313.0, 2313.0] },
      { "customer":  79, "arrival_starting": [2400.0, 2400.0] },
      { "customer":  96, "arrival_starting": [2897.0, 2897.0] },
      { "customer":  64, "arrival_starting": [3364.0, 3364.0] },
      { "customer":  25, "arrival_starting": [3647.0, 3647.0] },
      { "customer":  65, "arrival_starting": [3970.0, 3970.0] },
      { "customer":  69, "arrival_starting": [4370.0, 4370.0] },
      { "customer":  21, "arrival_starting": [4556.0, 4556.0] },
      { "customer":  15, "arrival_starting": [4626.0, 4626.0] },
      { "customer":  87, "arrival_starting": [4684.0, 4684.0] },
      { "customer":  17, "arrival_starting": [5030.0, 5030.0] },
      { "customer":  37, "arrival_starting": [5307.0, 5307.0] },
      { "customer":  98, "arrival_starting": [5620.0, 5620.0] },
      { "customer":  83, "arrival_starting": [6213.0, 6213.0] },
      { "customer":   9, "arrival_starting": [6353.0, 6353.0] },
      { "customer":  71, "arrival_starting": [6623.0, 6623.0] },
      { "customer":  20, "arrival_starting": [6775.0, 6775.0] },
      { "customer":  73, "arrival_starting": [6841.0, 6841.0] },
      { "customer":  58, "arrival_starting": [6930.0, 8874.0] },
      { "customer":  14, "arrival_starting": [9244.0, 9244.0] },
      { "customer":  10, "arrival_starting": [9357.0, 9357.0] },
      { "customer":  31, "arrival_starting": [9559.0, 9559.0] },
      { "customer":  44, "arrival_starting": [9781.0, 9781.0] },
      { "customer":  90, "arrival_starting": [9960.0, 9960.0] },
      { "customer":  97, "arrival_starting": [10059.0, 10059.0] },
      { "customer":  22, "arrival_starting": [10167.0, 10167.0] },
      { "customer":  76, "arrival_starting": [10549.0, 10549.0] },
      { "customer":  59, "arrival_starting": [10740.0, 10740.0] },
      { "customer":  61, "arrival_starting": [10891.0, 10891.0] },
      { "customer":  19, "arrival_starting": [11207.0, 11207.0] },
      { "customer":  56, "arrival_starting": [11411.0, 11411.0] },
      { "customer":   8, "arrival_starting": [11511.0, 11511.0] },
      { "customer":   6, "arrival_starting": [11561.0, 11561.0] },
      { "customer":  11, "arrival_starting": [11777.0, 11777.0] },
      { "customer":  54, "arrival_starting": [12007.0, 12007.0] },
      { "customer":  33, "arrival_starting": [12176.0, 12176.0] },
      { "customer":  28, "arrival_starting": [12477.0, 12477.0] },
      { "customer":  42, "arrival_starting": [12815.0, 12815.0] },
      { "customer":   2, "arrival_starting": [12986.0, 12986.0] },
      { "customer":  13, "arrival_starting": [13207.0, 13207.0] },
      { "customer":  99, "arrival_starting": [13475.0, 13475.0] },
      { "customer":  47, "arrival_starting": [13727.0, 13727.0] },
      { "customer":  29, "arrival_starting": [14154.0, 14154.0] },
      { "customer":  84, "arrival_starting": [14605.0, 14605.0] },
      { "customer":  38, "arrival_starting": [14977.0, 14977.0] },
      { "customer":  95, "arrival_starting": [15261.0, 15261.0] },
      { "customer":  77, "arrival_starting": [15329.0, 15329.0] },
      { "customer":  51, "arrival_starting": [15369.0, 15369.0] },
      { "customer":   4, "arrival_starting": [15628.0, 15628.0] },
      { "customer":  36, "arrival_starting": [15697.0, 15697.0] },
      { "customer":  32, "arrival_starting": [16105.0, 16105.0] },
      { "customer":  12, "arrival_starting": [16206.0, 16206.0] },
      { "customer":  94, "arrival_starting": [16422.0, 16422.0] },
      { "customer":  81, "arrival_starting": [16667.0, 16667.0] },
      { "customer":  49, "arrival_starting": [17182.0, 17182.0] },
      { "customer":  72, "arrival_starting": [17362.0, 17362.0] },
      { "customer":  63, "arrival_starting": [17738.0, 17738.0] },
      { "customer":  39, "arrival_starting": [17818.0, 17818.0] },
      { "customer":  68, "arrival_starting": [18182.0, 18182.0] },
      { "customer":  80, "arrival_starting": [18485.0, 18485.0] },
      { "customer":  86, "arrival_starting": [18870.0, 18870.0] },
      { "customer":  50, "arrival_starting": [19016.0, 19016.0] },
      { "customer":  57, "arrival_starting": [19451.0, 19451.0] },
      { "customer":  27, "arrival_starting": [19754.0, 19754.0] },
      { "customer":  92, "arrival_starting": [19802.0, 19802.0] },
      { "customer":  46, "arrival_starting": [20335.0, 20335.0] },
      { "customer":   0, "arrival_starting": [20764.0, 20764.0] }
    ]
  },
  {
    "route": 5,
    "tasks": 
    [
      { "customer":   0, "arrival_starting": [   0.0,    0.0] },
      { "customer":  62, "arrival_starting": [ 288.0,  288.0] },
      { "customer":  48, "arrival_starting": [ 490.0,  490.0] },
      { "customer":  89, "arrival_starting": [ 698.0,  698.0] },
      { "customer":  18, "arrival_starting": [1074.0, 1074.0] },
      { "customer":  74, "arrival_starting": [1308.0, 1308.0] },
      { "customer":  91, "arrival_starting": [1666.0, 1666.0] },
      { "customer":  88, "arrival_starting": [2287.0, 2287.0] },
      { "customer":  79, "arrival_starting": [2540.0, 2540.0] },
      { "customer":  55, "arrival_starting": [2821.0, 2821.0] },
      { "customer":  96, "arrival_starting": [3037.0, 3037.0] },
      { "customer":   3, "arrival_starting": [3361.0, 3361.0] },
      { "customer":  64, "arrival_starting": [3508.0, 3508.0] },
      { "customer":  25, "arrival_starting": [3791.0, 3791.0] },
      { "customer":  65, "arrival_starting": [4114.0, 4114.0] },
      { "customer":  69, "arrival_starting": [4514.0, 4514.0] },
      { "customer":  21, "arrival_starting": [4700.0, 4700.0] },
      { "customer":  93, "arrival_starting": [4834.0, 4834.0] },
      { "customer":  15, "arrival_starting": [4995.0, 4995.0] },
      { "customer":  52, "arrival_starting": [5251.0, 5251.0] },
      { "customer":  78, "arrival_starting": [5474.0, 5474.0] },
      { "customer":  17, "arrival_starting": [5704.0, 5704.0] },
      { "customer":  23, "arrival_starting": [5885.0, 5885.0] },
      { "customer":  37, "arrival_starting": [5981.0, 5981.0] },
      { "customer":  35, "arrival_starting": [6209.0, 6209.0] },
      { "customer":  83, "arrival_starting": [6531.0, 6531.0] },
      { "customer":  71, "arrival_starting": [6845.0, 6845.0] },
      { "customer":  20, "arrival_starting": [6997.0, 6997.0] },
      { "customer":  73, "arrival_starting": [7063.0, 7063.0] },
      { "customer":  58, "arrival_starting": [7152.0, 7152.0] },
      { "customer":  16, "arrival_starting": [7510.0, 7510.0] },
      { "customer":  14, "arrival_starting": [7523.0, 7523.0] },
      { "customer":  31, "arrival_starting": [7803.0, 7803.0] },
      { "customer":  44, "arrival_starting": [8025.0, 8025.0] },
      { "customer":  22, "arrival_starting": [8246.0, 8246.0] },
      { "customer":  59, "arrival_starting": [8591.0, 8591.0] },
      { "customer":  61, "arrival_starting": [8742.0, 8742.0] },
      { "customer":  19, "arrival_starting": [9058.0, 9058.0] },
      { "customer":  26, "arrival_starting": [9239.0, 9239.0] },
      { "customer":  11, "arrival_starting": [9375.0, 9375.0] },
      { "customer":  56, "arrival_starting": [9616.0, 9616.0] },
      { "customer":   8, "arrival_starting": [9716.0, 9716.0] },
      { "customer":  54, "arrival_starting": [10014.0, 10014.0] },
      { "customer":  82, "arrival_starting": [10037.0, 10037.0] },
      { "customer":  28, "arrival_starting": [10473.0, 10473.0] },
      { "customer":  45, "arrival_starting": [10621.0, 10621.0] },
      { "customer":   2, "arrival_starting": [10760.0, 10760.0] },
      { "customer":  13, "arrival_starting": [10981.0, 10981.0] },
      { "customer":  47, "arrival_starting": [11269.0, 11269.0] },
      { "customer":  29, "arrival_starting": [11696.0, 11696.0] },
      { "customer":  77, "arrival_starting": [12048.0, 12048.0] },
      { "customer":   4, "arrival_starting": [12290.0, 12290.0] },
      { "customer":  36, "arrival_starting": [12359.0, 12359.0] },
      { "customer":  32, "arrival_starting": [12767.0, 12767.0] },
      { "customer":  94, "arrival_starting": [13078.0, 13078.0] },
      { "customer":  84, "arrival_starting": [14071.0, 14071.0] },
      { "customer":  67, "arrival_starting": [14224.0, 14224.0] },
      { "customer":  49, "arrival_starting": [14544.0, 14544.0] },
      { "customer":  43, "arrival_starting": [14706.0, 14706.0] },
      { "customer":  53, "arrival_starting": [15169.0, 15169.0] },
      { "customer":  39, "arrival_starting": [15273.0, 15273.0] },
      { "customer":  63, "arrival_starting": [15353.0, 15353.0] },
      { "customer":  68, "arrival_starting": [15650.0, 15650.0] },
      { "customer":  80, "arrival_starting": [15953.0, 15953.0] },
      { "customer":  50, "arrival_starting": [16258.0, 16258.0] },
      { "customer":  60, "arrival_starting": [16444.0, 16444.0] },
      { "customer":  66, "arrival_starting": [17041.0, 17041.0] },
      { "customer":  27, "arrival_starting": [17342.0, 17342.0] },
      { "customer":   0, "arrival_starting": [17758.0, 17758.0] }
    ]
  }
  ]

}

