{
  "instance_name": "kroB100_p5_f90_lM",

  "schedule": 
  [
  {
    "route": 1,
    "tasks": 
    [
      { "customer":   0, "arrival_starting": [   0.0,    0.0] },
      { "customer":  11, "arrival_starting": [ 263.0,  439.0] },
      { "customer":  70, "arrival_starting": [ 636.0,  636.0] },
      { "customer":  26, "arrival_starting": [ 896.0,  896.0] },
      { "customer":  60, "arrival_starting": [1137.0, 1137.0] },
      { "customer":  93, "arrival_starting": [1411.0, 1411.0] },
      { "customer":  56, "arrival_starting": [1569.0, 1569.0] },
      { "customer":  59, "arrival_starting": [1977.0, 1977.0] },
      { "customer":  65, "arrival_starting": [2404.0, 2404.0] },
      { "customer":  86, "arrival_starting": [2760.0, 4634.0] },
      { "customer":  88, "arrival_starting": [4942.0, 4942.0] },
      { "customer":  42, "arrival_starting": [5152.0, 5152.0] },
      { "customer":  49, "arrival_starting": [5501.0, 5501.0] },
      { "customer":  15, "arrival_starting": [5965.0, 5965.0] },
      { "customer":   1, "arrival_starting": [6201.0, 6201.0] },
      { "customer":  41, "arrival_starting": [6418.0, 6418.0] },
      { "customer":  63, "arrival_starting": [6672.0, 6672.0] },
      { "customer":  82, "arrival_starting": [7034.0, 7034.0] },
      { "customer":   3, "arrival_starting": [7255.0, 7255.0] },
      { "customer":   5, "arrival_starting": [7479.0, 7479.0] },
      { "customer":  14, "arrival_starting": [7737.0, 7737.0] },
      { "customer":  32, "arrival_starting": [7923.0, 7923.0] },
      { "customer":  81, "arrival_starting": [8206.0, 8206.0] },
      { "customer":  50, "arrival_starting": [8843.0, 8843.0] },
      { "customer":  30, "arrival_starting": [9342.0, 9342.0] },
      { "customer":  62, "arrival_starting": [9508.0, 9508.0] },
      { "customer":  12, "arrival_starting": [9773.0, 9773.0] },
      { "customer":  77, "arrival_starting": [9943.0, 9943.0] },
      { "customer":  40, "arrival_starting": [10349.0, 10349.0] },
      { "customer":  43, "arrival_starting": [10796.0, 10796.0] },
      { "customer":  18, "arrival_starting": [11140.0, 11140.0] },
      { "customer":  91, "arrival_starting": [11214.0, 11214.0] },
      { "customer":  95, "arrival_starting": [11352.0, 11352.0] },
      { "customer":  35, "arrival_starting": [11534.0, 11534.0] },
      { "customer":  44, "arrival_starting": [11611.0, 11611.0] },
      { "customer":  17, "arrival_starting": [11883.0, 11883.0] },
      { "customer":  23, "arrival_starting": [12036.0, 12036.0] },
      { "customer":  76, "arrival_starting": [12228.0, 12228.0] },
      { "customer":  54, "arrival_starting": [12648.0, 12648.0] },
      { "customer":  21, "arrival_starting": [13014.0, 13014.0] },
      { "customer":  22, "arrival_starting": [13061.0, 13061.0] },
      { "customer":  87, "arrival_starting": [13189.0, 13189.0] },
      { "customer":  53, "arrival_starting": [13719.0, 13719.0] },
      { "customer":  51, "arrival_starting": [13908.0, 13908.0] },
      { "customer":  57, "arrival_starting": [14154.0, 14154.0] },
      { "customer":  83, "arrival_starting": [14208.0, 14208.0] },
      { "customer":   6, "arrival_starting": [14239.0, 14239.0] },
      { "customer":  33, "arrival_starting": [14533.0, 14533.0] },
      { "customer":   8, "arrival_starting": [14863.0, 14863.0] },
      { "customer":  24, "arrival_starting": [14893.0, 14893.0] },
      { "customer":  45, "arrival_starting": [14955.0, 14955.0] },
      { "customer":  89, "arrival_starting": [15319.0, 15319.0] },
      { "customer":   9, "arrival_starting": [15853.0, 15853.0] },
      { "customer":  85, "arrival_starting": [16229.0, 16229.0] },
      { "customer":  48, "arrival_starting": [16255.0, 16255.0] },
      { "customer":  29, "arrival_starting": [16507.0, 16507.0] },
      { "customer":  74, "arrival_starting": [16566.0, 16566.0] },
      { "customer":  79, "arrival_starting": [16778.0, 16778.0] },
      { "customer":  19, "arrival_starting": [16820.0, 16820.0] },
      { "customer":  37, "arrival_starting": [16905.0, 16905.0] },
      { "customer":  71, "arrival_starting": [17406.0, 17406.0] },
      { "customer":  36, "arrival_starting": [17514.0, 17514.0] },
      { "customer":  46, "arrival_starting": [18026.0, 18026.0] },
      { "customer":  78, "arrival_starting": [18277.0, 18277.0] },
      { "customer":  80, "arrival_starting": [18453.0, 18453.0] },
      { "customer":  99, "arrival_starting": [18904.0, 18904.0] },
      { "customer":  25, "arrival_starting": [18992.0, 18992.0] },
      { "customer":  68, "arrival_starting": [19147.0, 19147.0] },
      { "customer":  61, "arrival_starting": [19398.0, 19398.0] },
      { "customer":   4, "arrival_starting": [19704.0, 19704.0] },
      { "customer":  66, "arrival_starting": [19933.0, 19933.0] },
      { "customer":  39, "arrival_starting": [20261.0, 20261.0] },
      { "customer":  38, "arrival_starting": [20421.0, 20421.0] },
      { "customer":  69, "arrival_starting": [20530.0, 20530.0] },
      { "customer":  52, "arrival_starting": [20760.0, 20760.0] },
      { "customer":  72, "arrival_starting": [21107.0, 21107.0] },
      { "customer":  84, "arrival_starting": [21195.0, 21195.0] },
      { "customer":  92, "arrival_starting": [21475.0, 21475.0] },
      { "customer":  10, "arrival_starting": [21529.0, 21529.0] },
      { "customer":   2, "arrival_starting": [21719.0, 21719.0] },
      { "customer":  27, "arrival_starting": [22063.0, 22063.0] },
      { "customer":  90, "arrival_starting": [22127.0, 22127.0] },
      { "customer":  96, "arrival_starting": [22327.0, 22327.0] },
      { "customer":  98, "arrival_starting": [22449.0, 22449.0] },
      { "customer":   7, "arrival_starting": [22491.0, 22491.0] },
      { "customer":  28, "arrival_starting": [22591.0, 22591.0] },
      { "customer":  75, "arrival_starting": [22784.0, 22784.0] },
      { "customer":  58, "arrival_starting": [22924.0, 22924.0] },
      { "customer":  31, "arrival_starting": [23080.0, 23080.0] },
      { "customer":  97, "arrival_starting": [23318.0, 23318.0] },
      { "customer":   0, "arrival_starting": [23547.0, 23547.0] }
    ]
  },
  {
    "route": 2,
    "tasks": 
    [
      { "customer":   0, "arrival_starting": [   0.0,    0.0] },
      { "customer":  11, "arrival_starting": [ 263.0,  439.0] },
      { "customer":  70, "arrival_starting": [ 636.0,  636.0] },
      { "customer":  26, "arrival_starting": [ 896.0,  896.0] },
      { "customer":  60, "arrival_starting": [1137.0, 1137.0] },
      { "customer":  34, "arrival_starting": [1243.0, 1243.0] },
      { "customer":  93, "arrival_starting": [1602.0, 1602.0] },
      { "customer":  56, "arrival_starting": [1760.0, 1760.0] },
      { "customer":  59, "arrival_starting": [2168.0, 2168.0] },
      { "customer":  73, "arrival_starting": [2280.0, 2280.0] },
      { "customer":  65, "arrival_starting": [2629.0, 2629.0] },
      { "customer":  86, "arrival_starting": [2985.0, 2985.0] },
      { "customer":  88, "arrival_starting": [3293.0, 3293.0] },
      { "customer":  49, "arrival_starting": [3755.0, 3755.0] },
      { "customer":  15, "arrival_starting": [4219.0, 4219.0] },
      { "customer":   1, "arrival_starting": [4455.0, 4455.0] },
      { "customer":  41, "arrival_starting": [4672.0, 4672.0] },
      { "customer":  13, "arrival_starting": [4904.0, 4904.0] },
      { "customer":  63, "arrival_starting": [5025.0, 5025.0] },
      { "customer":  82, "arrival_starting": [5387.0, 5387.0] },
      { "customer":   5, "arrival_starting": [5662.0, 5662.0] },
      { "customer":  14, "arrival_starting": [5920.0, 5920.0] },
      { "customer":  32, "arrival_starting": [6106.0, 6106.0] },
      { "customer":  81, "arrival_starting": [6389.0, 6389.0] },
      { "customer":  50, "arrival_starting": [7026.0, 7026.0] },
      { "customer":  47, "arrival_starting": [7487.0, 7487.0] },
      { "customer":  30, "arrival_starting": [7612.0, 7612.0] },
      { "customer":  62, "arrival_starting": [7778.0, 7778.0] },
      { "customer":  12, "arrival_starting": [8043.0, 8043.0] },
      { "customer":  77, "arrival_starting": [8213.0, 8213.0] },
      { "customer":  16, "arrival_starting": [8469.0, 8469.0] },
      { "customer":  40, "arrival_starting": [8631.0, 8631.0] },
      { "customer":  43, "arrival_starting": [9078.0, 9078.0] },
      { "customer":  91, "arrival_starting": [9411.0, 9411.0] },
      { "customer":  95, "arrival_starting": [9549.0, 9549.0] },
      { "customer":  35, "arrival_starting": [9731.0, 9731.0] },
      { "customer":  44, "arrival_starting": [9808.0, 9808.0] },
      { "customer":  17, "arrival_starting": [10080.0, 10080.0] },
      { "customer":  23, "arrival_starting": [10233.0, 10233.0] },
      { "customer":  76, "arrival_starting": [10425.0, 10425.0] },
      { "customer":  54, "arrival_starting": [10845.0, 10845.0] },
      { "customer":  21, "arrival_starting": [11211.0, 11211.0] },
      { "customer":  22, "arrival_starting": [11258.0, 11258.0] },
      { "customer":  87, "arrival_starting": [11386.0, 11386.0] },
      { "customer":  53, "arrival_starting": [11916.0, 11916.0] },
      { "customer":  57, "arrival_starting": [12260.0, 12260.0] },
      { "customer":  83, "arrival_starting": [12314.0, 12314.0] },
      { "customer":   6, "arrival_starting": [12345.0, 12345.0] },
      { "customer":  33, "arrival_starting": [12639.0, 12639.0] },
      { "customer":   8, "arrival_starting": [12969.0, 12969.0] },
      { "customer":  24, "arrival_starting": [12999.0, 12999.0] },
      { "customer":  45, "arrival_starting": [13061.0, 13061.0] },
      { "customer":  89, "arrival_starting": [13425.0, 13425.0] },
      { "customer":  20, "arrival_starting": [13578.0, 13578.0] },
      { "customer":   9, "arrival_starting": [13967.0, 13967.0] },
      { "customer":  67, "arrival_starting": [14096.0, 14096.0] },
      { "customer":  48, "arrival_starting": [14385.0, 14385.0] },
      { "customer":  29, "arrival_starting": [14637.0, 14637.0] },
      { "customer":  74, "arrival_starting": [14696.0, 14696.0] },
      { "customer":  79, "arrival_starting": [14908.0, 14908.0] },
      { "customer":  19, "arrival_starting": [14950.0, 14950.0] },
      { "customer":  37, "arrival_starting": [15035.0, 15035.0] },
      { "customer":  71, "arrival_starting": [15536.0, 15536.0] },
      { "customer":  36, "arrival_starting": [15644.0, 15644.0] },
      { "customer":  64, "arrival_starting": [15987.0, 15987.0] },
      { "customer":  46, "arrival_starting": [16247.0, 16247.0] },
      { "customer":  78, "arrival_starting": [16498.0, 16498.0] },
      { "customer":  80, "arrival_starting": [16674.0, 16674.0] },
      { "customer":  55, "arrival_starting": [17071.0, 17071.0] },
      { "customer":  99, "arrival_starting": [17135.0, 17135.0] },
      { "customer":  25, "arrival_starting": [17223.0, 17223.0] },
      { "customer":  68, "arrival_starting": [17378.0, 17378.0] },
      { "customer":  61, "arrival_starting": [17629.0, 17629.0] },
      { "customer":   4, "arrival_starting": [17935.0, 17935.0] },
      { "customer":  66, "arrival_starting": [18164.0, 18164.0] },
      { "customer":  39, "arrival_starting": [18492.0, 18492.0] },
      { "customer":  38, "arrival_starting": [18652.0, 18652.0] },
      { "customer":  69, "arrival_starting": [18761.0, 18761.0] },
      { "customer":  52, "arrival_starting": [18991.0, 18991.0] },
      { "customer":  72, "arrival_starting": [19338.0, 19338.0] },
      { "customer":  84, "arrival_starting": [19426.0, 19426.0] },
      { "customer":  92, "arrival_starting": [19706.0, 19706.0] },
      { "customer":  10, "arrival_starting": [19760.0, 19760.0] },
      { "customer":   2, "arrival_starting": [19950.0, 19950.0] },
      { "customer":  27, "arrival_starting": [20294.0, 20294.0] },
      { "customer":  96, "arrival_starting": [20558.0, 20558.0] },
      { "customer":  98, "arrival_starting": [20680.0, 20680.0] },
      { "customer":   7, "arrival_starting": [20722.0, 20722.0] },
      { "customer":  28, "arrival_starting": [20822.0, 20822.0] },
      { "customer":  75, "arrival_starting": [21015.0, 21015.0] },
      { "customer":  58, "arrival_starting": [21155.0, 21155.0] },
      { "customer":  31, "arrival_starting": [21311.0, 21311.0] },
      { "customer":  97, "arrival_starting": [21549.0, 21549.0] },
      { "customer":  94, "arrival_starting": [21754.0, 21754.0] },
      { "customer":   0, "arrival_starting": [21850.0, 21850.0] }
    ]
  },
  {
    "route": 3,
    "tasks": 
    [
      { "customer":   0, "arrival_starting": [   0.0,    0.0] },
      { "customer":  70, "arrival_starting": [ 439.0,  439.0] },
      { "customer":  26, "arrival_starting": [ 699.0,  699.0] },
      { "customer":  60, "arrival_starting": [ 940.0,  940.0] },
      { "customer":  34, "arrival_starting": [1046.0, 1046.0] },
      { "customer":  93, "arrival_starting": [1405.0, 1405.0] },
      { "customer":  56, "arrival_starting": [1563.0, 1563.0] },
      { "customer":  59, "arrival_starting": [1971.0, 1971.0] },
      { "customer":  73, "arrival_starting": [2083.0, 2083.0] },
      { "customer":  65, "arrival_starting": [2432.0, 2432.0] },
      { "customer":  86, "arrival_starting": [2788.0, 2788.0] },
      { "customer":  88, "arrival_starting": [3096.0, 3096.0] },
      { "customer":  42, "arrival_starting": [3306.0, 3306.0] },
      { "customer":  15, "arrival_starting": [4074.0, 4074.0] },
      { "customer":   1, "arrival_starting": [4310.0, 4310.0] },
      { "customer":  41, "arrival_starting": [4527.0, 4527.0] },
      { "customer":  13, "arrival_starting": [4759.0, 4759.0] },
      { "customer":  82, "arrival_starting": [5148.0, 5148.0] },
      { "customer":   3, "arrival_starting": [5369.0, 5369.0] },
      { "customer":   5, "arrival_starting": [5593.0, 5593.0] },
      { "customer":  14, "arrival_starting": [5851.0, 5851.0] },
      { "customer":  32, "arrival_starting": [6037.0, 6037.0] },
      { "customer":  81, "arrival_starting": [6320.0, 6320.0] },
      { "customer":  47, "arrival_starting": [6725.0, 6725.0] },
      { "customer":  30, "arrival_starting": [6850.0, 6850.0] },
      { "customer":  62, "arrival_starting": [7016.0, 7016.0] },
      { "customer":  12, "arrival_starting": [7281.0, 7281.0] },
      { "customer":  77, "arrival_starting": [7451.0, 7451.0] },
      { "customer":  40, "arrival_starting": [7857.0, 7857.0] },
      { "customer":  43, "arrival_starting": [8304.0, 8304.0] },
      { "customer":  18, "arrival_starting": [8648.0, 8648.0] },
      { "customer":  95, "arrival_starting": [8800.0, 8800.0] },
      { "customer":  35, "arrival_starting": [8982.0, 8982.0] },
      { "customer":  44, "arrival_starting": [9059.0, 9059.0] },
      { "customer":  17, "arrival_starting": [9331.0, 9331.0] },
      { "customer":  23, "arrival_starting": [9484.0, 9484.0] },
      { "customer":  76, "arrival_starting": [9676.0, 9676.0] },
      { "customer":  21, "arrival_starting": [10437.0, 10437.0] },
      { "customer":  22, "arrival_starting": [10484.0, 10484.0] },
      { "customer":  57, "arrival_starting": [11483.0, 11483.0] },
      { "customer":  83, "arrival_starting": [11537.0, 11537.0] },
      { "customer":   6, "arrival_starting": [11568.0, 11568.0] },
      { "customer":  33, "arrival_starting": [11862.0, 11862.0] },
      { "customer":  24, "arrival_starting": [12190.0, 12190.0] },
      { "customer":  45, "arrival_starting": [12252.0, 12252.0] },
      { "customer":  89, "arrival_starting": [12616.0, 12616.0] },
      { "customer":  20, "arrival_starting": [12769.0, 12769.0] },
      { "customer":   9, "arrival_starting": [13158.0, 13158.0] },
      { "customer":  67, "arrival_starting": [13287.0, 13287.0] },
      { "customer":  85, "arrival_starting": [13574.0, 13574.0] },
      { "customer":  48, "arrival_starting": [13600.0, 13600.0] },
      { "customer":  29, "arrival_starting": [13852.0, 13852.0] },
      { "customer":  79, "arrival_starting": [14028.0, 14028.0] },
      { "customer":  19, "arrival_starting": [14070.0, 14070.0] },
      { "customer":  71, "arrival_starting": [14543.0, 14543.0] },
      { "customer":  64, "arrival_starting": [14969.0, 14969.0] },
      { "customer":  46, "arrival_starting": [15229.0, 15229.0] },
      { "customer":  78, "arrival_starting": [15480.0, 15480.0] },
      { "customer":  80, "arrival_starting": [15656.0, 15656.0] },
      { "customer":  55, "arrival_starting": [16053.0, 16053.0] },
      { "customer":  99, "arrival_starting": [16117.0, 16117.0] },
      { "customer":  25, "arrival_starting": [16205.0, 16205.0] },
      { "customer":  68, "arrival_starting": [16360.0, 16360.0] },
      { "customer":  61, "arrival_starting": [16611.0, 16611.0] },
      { "customer":   4, "arrival_starting": [16917.0, 16917.0] },
      { "customer":  66, "arrival_starting": [17146.0, 17146.0] },
      { "customer":  38, "arrival_starting": [17512.0, 17512.0] },
      { "customer":  52, "arrival_starting": [17751.0, 17751.0] },
      { "customer":  72, "arrival_starting": [18098.0, 18098.0] },
      { "customer":  92, "arrival_starting": [18454.0, 18454.0] },
      { "customer":  10, "arrival_starting": [18508.0, 18508.0] },
      { "customer":   2, "arrival_starting": [18698.0, 18698.0] },
      { "customer":  27, "arrival_starting": [19042.0, 19042.0] },
      { "customer":  90, "arrival_starting": [19106.0, 19106.0] },
      { "customer":  96, "arrival_starting": [19306.0, 19306.0] },
      { "customer":  98, "arrival_starting": [19428.0, 19428.0] },
      { "customer":   7, "arrival_starting": [19470.0, 19470.0] },
      { "customer":  75, "arrival_starting": [19627.0, 19627.0] },
      { "customer":  58, "arrival_starting": [19767.0, 19767.0] },
      { "customer":  31, "arrival_starting": [19923.0, 19923.0] },
      { "customer":  97, "arrival_starting": [20161.0, 20161.0] },
      { "customer":  94, "arrival_starting": [20366.0, 20366.0] },
      { "customer":   0, "arrival_starting": [20462.0, 20462.0] }
    ]
  },
  {
    "route": 4,
    "tasks": 
    [
      { "customer":   0, "arrival_starting": [   0.0,    0.0] },
      { "customer":  11, "arrival_starting": [ 263.0,  439.0] },
      { "customer":  70, "arrival_starting": [ 636.0,  636.0] },
      { "customer":  60, "arrival_starting": [1007.0, 1007.0] },
      { "customer":  93, "arrival_starting": [1281.0, 1281.0] },
      { "customer":  56, "arrival_starting": [1439.0, 1439.0] },
      { "customer":  73, "arrival_starting": [1812.0, 1812.0] },
      { "customer":  59, "arrival_starting": [1924.0, 1924.0] },
      { "customer":  86, "arrival_starting": [2157.0, 2157.0] },
      { "customer":  88, "arrival_starting": [2465.0, 2465.0] },
      { "customer":  49, "arrival_starting": [2927.0, 2927.0] },
      { "customer":  15, "arrival_starting": [3391.0, 3391.0] },
      { "customer":   1, "arrival_starting": [3627.0, 3627.0] },
      { "customer":  41, "arrival_starting": [3844.0, 3844.0] },
      { "customer":   3, "arrival_starting": [4655.0, 4655.0] },
      { "customer":   5, "arrival_starting": [4879.0, 4879.0] },
      { "customer":  14, "arrival_starting": [5137.0, 5137.0] },
      { "customer":  81, "arrival_starting": [5573.0, 5573.0] },
      { "customer":  47, "arrival_starting": [5978.0, 5978.0] },
      { "customer":  30, "arrival_starting": [6103.0, 6103.0] },
      { "customer":  62, "arrival_starting": [6269.0, 6269.0] },
      { "customer":  12, "arrival_starting": [6534.0, 6534.0] },
      { "customer":  77, "arrival_starting": [6704.0, 6704.0] },
      { "customer":  16, "arrival_starting": [6960.0, 6960.0] },
      { "customer":  40, "arrival_starting": [7122.0, 7122.0] },
      { "customer":  43, "arrival_starting": [7569.0, 7569.0] },
      { "customer":  18, "arrival_starting": [7913.0, 7913.0] },
      { "customer":  91, "arrival_starting": [7987.0, 7987.0] },
      { "customer":  95, "arrival_starting": [8125.0, 8125.0] },
      { "customer":  35, "arrival_starting": [8307.0, 8307.0] },
      { "customer":  44, "arrival_starting": [8384.0, 8384.0] },
      { "customer":  17, "arrival_starting": [8656.0, 8656.0] },
      { "customer":  23, "arrival_starting": [8809.0, 8809.0] },
      { "customer":  76, "arrival_starting": [9001.0, 9001.0] },
      { "customer":  54, "arrival_starting": [9421.0, 9421.0] },
      { "customer":  21, "arrival_starting": [9787.0, 9787.0] },
      { "customer":  22, "arrival_starting": [9834.0, 9834.0] },
      { "customer":  87, "arrival_starting": [9962.0, 9962.0] },
      { "customer":  53, "arrival_starting": [10492.0, 10492.0] },
      { "customer":  51, "arrival_starting": [10681.0, 10681.0] },
      { "customer":  57, "arrival_starting": [10927.0, 10927.0] },
      { "customer":  83, "arrival_starting": [10981.0, 10981.0] },
      { "customer":   6, "arrival_starting": [11012.0, 11012.0] },
      { "customer":  33, "arrival_starting": [11306.0, 11306.0] },
      { "customer":   8, "arrival_starting": [11636.0, 11669.0] },
      { "customer":  89, "arrival_starting": [12085.0, 12085.0] },
      { "customer":   9, "arrival_starting": [12619.0, 12619.0] },
      { "customer":  85, "arrival_starting": [12995.0, 12995.0] },
      { "customer":  29, "arrival_starting": [13268.0, 13268.0] },
      { "customer":  74, "arrival_starting": [13327.0, 13327.0] },
      { "customer":  79, "arrival_starting": [13539.0, 13539.0] },
      { "customer":  19, "arrival_starting": [13581.0, 13581.0] },
      { "customer":  37, "arrival_starting": [13666.0, 13666.0] },
      { "customer":  36, "arrival_starting": [14205.0, 14275.0] },
      { "customer":  64, "arrival_starting": [14618.0, 14618.0] },
      { "customer":  46, "arrival_starting": [14878.0, 14878.0] },
      { "customer":  78, "arrival_starting": [15129.0, 15129.0] },
      { "customer":  80, "arrival_starting": [15305.0, 15305.0] },
      { "customer":  55, "arrival_starting": [15702.0, 15702.0] },
      { "customer":  25, "arrival_starting": [15854.0, 15854.0] },
      { "customer":  68, "arrival_starting": [16009.0, 16009.0] },
      { "customer":  61, "arrival_starting": [16260.0, 16260.0] },
      { "customer":   4, "arrival_starting": [16566.0, 16566.0] },
      { "customer":  66, "arrival_starting": [16795.0, 16795.0] },
      { "customer":  39, "arrival_starting": [17123.0, 17123.0] },
      { "customer":  38, "arrival_starting": [17283.0, 17283.0] },
      { "customer":  69, "arrival_starting": [17392.0, 17392.0] },
      { "customer":  52, "arrival_starting": [17622.0, 17622.0] },
      { "customer":  72, "arrival_starting": [17969.0, 17969.0] },
      { "customer":  84, "arrival_starting": [18057.0, 18057.0] },
      { "customer":  92, "arrival_starting": [18337.0, 18337.0] },
      { "customer":  10, "arrival_starting": [18391.0, 18468.0] },
      { "customer":  27, "arrival_starting": [18824.0, 18824.0] },
      { "customer":  90, "arrival_starting": [18888.0, 18888.0] },
      { "customer":  96, "arrival_starting": [19088.0, 19088.0] },
      { "customer":  98, "arrival_starting": [19210.0, 19210.0] },
      { "customer":   7, "arrival_starting": [19252.0, 19406.0] },
      { "customer":  28, "arrival_starting": [19506.0, 19506.0] },
      { "customer":  75, "arrival_starting": [19699.0, 19699.0] },
      { "customer":  58, "arrival_starting": [19839.0, 19839.0] },
      { "customer":  31, "arrival_starting": [19995.0, 19995.0] },
      { "customer":  97, "arrival_starting": [20233.0, 20233.0] },
      { "customer":  94, "arrival_starting": [20438.0, 20438.0] },
      { "customer":   0, "arrival_starting": [20534.0, 20534.0] }
    ]
  },
  {
    "route": 5,
    "tasks": 
    [
      { "customer":   0, "arrival_starting": [   0.0,    0.0] },
      { "customer":  11, "arrival_starting": [ 263.0,  439.0] },
      { "customer":  70, "arrival_starting": [ 636.0,  636.0] },
      { "customer":  34, "arrival_starting": [1050.0, 1050.0] },
      { "customer":  60, "arrival_starting": [1156.0, 1156.0] },
      { "customer":  93, "arrival_starting": [1430.0, 1430.0] },
      { "customer":  56, "arrival_starting": [1588.0, 1588.0] },
      { "customer":  59, "arrival_starting": [1996.0, 1996.0] },
      { "customer":  73, "arrival_starting": [2108.0, 2108.0] },
      { "customer":  65, "arrival_starting": [2457.0, 2457.0] },
      { "customer":  86, "arrival_starting": [2813.0, 2813.0] },
      { "customer":  88, "arrival_starting": [3121.0, 3121.0] },
      { "customer":  42, "arrival_starting": [3331.0, 3331.0] },
      { "customer":  49, "arrival_starting": [3680.0, 3680.0] },
      { "customer":  15, "arrival_starting": [4144.0, 4144.0] },
      { "customer":   1, "arrival_starting": [4380.0, 4380.0] },
      { "customer":  41, "arrival_starting": [4597.0, 4597.0] },
      { "customer":  13, "arrival_starting": [4829.0, 4829.0] },
      { "customer":  63, "arrival_starting": [4950.0, 4950.0] },
      { "customer":  82, "arrival_starting": [5312.0, 5312.0] },
      { "customer":   3, "arrival_starting": [5533.0, 5533.0] },
      { "customer":   5, "arrival_starting": [5757.0, 5757.0] },
      { "customer":  14, "arrival_starting": [6015.0, 6015.0] },
      { "customer":  32, "arrival_starting": [6201.0, 6201.0] },
      { "customer":  81, "arrival_starting": [6484.0, 6484.0] },
      { "customer":  50, "arrival_starting": [7121.0, 7121.0] },
      { "customer":  30, "arrival_starting": [7620.0, 7620.0] },
      { "customer":  62, "arrival_starting": [7786.0, 7786.0] },
      { "customer":  12, "arrival_starting": [8051.0, 8051.0] },
      { "customer":  77, "arrival_starting": [8221.0, 8221.0] },
      { "customer":  16, "arrival_starting": [8477.0, 8477.0] },
      { "customer":  40, "arrival_starting": [8639.0, 8639.0] },
      { "customer":  43, "arrival_starting": [9086.0, 9086.0] },
      { "customer":  91, "arrival_starting": [9419.0, 9419.0] },
      { "customer":  95, "arrival_starting": [9557.0, 9557.0] },
      { "customer":  35, "arrival_starting": [9739.0, 9739.0] },
      { "customer":  44, "arrival_starting": [9816.0, 9816.0] },
      { "customer":  17, "arrival_starting": [10088.0, 10088.0] },
      { "customer":  23, "arrival_starting": [10241.0, 10241.0] },
      { "customer":  54, "arrival_starting": [10684.0, 10684.0] },
      { "customer":  21, "arrival_starting": [11050.0, 11050.0] },
      { "customer":  22, "arrival_starting": [11097.0, 11097.0] },
      { "customer":  87, "arrival_starting": [11225.0, 11225.0] },
      { "customer":  53, "arrival_starting": [11755.0, 11755.0] },
      { "customer":  51, "arrival_starting": [11944.0, 11944.0] },
      { "customer":  57, "arrival_starting": [12190.0, 12190.0] },
      { "customer":  83, "arrival_starting": [12244.0, 12244.0] },
      { "customer":   6, "arrival_starting": [12275.0, 12275.0] },
      { "customer":  33, "arrival_starting": [12569.0, 12569.0] },
      { "customer":  24, "arrival_starting": [12897.0, 12897.0] },
      { "customer":   8, "arrival_starting": [12927.0, 12927.0] },
      { "customer":  89, "arrival_starting": [13343.0, 13343.0] },
      { "customer":  20, "arrival_starting": [13496.0, 13496.0] },
      { "customer":   9, "arrival_starting": [13885.0, 13885.0] },
      { "customer":  67, "arrival_starting": [14014.0, 14014.0] },
      { "customer":  85, "arrival_starting": [14301.0, 14301.0] },
      { "customer":  48, "arrival_starting": [14327.0, 14327.0] },
      { "customer":  29, "arrival_starting": [14579.0, 14579.0] },
      { "customer":  74, "arrival_starting": [14638.0, 14638.0] },
      { "customer":  79, "arrival_starting": [14850.0, 14850.0] },
      { "customer":  19, "arrival_starting": [14892.0, 14892.0] },
      { "customer":  37, "arrival_starting": [14977.0, 14977.0] },
      { "customer":  71, "arrival_starting": [15478.0, 15478.0] },
      { "customer":  36, "arrival_starting": [15586.0, 15586.0] },
      { "customer":  64, "arrival_starting": [15929.0, 15929.0] },
      { "customer":  46, "arrival_starting": [16189.0, 16189.0] },
      { "customer":  78, "arrival_starting": [16440.0, 16440.0] },
      { "customer":  80, "arrival_starting": [16616.0, 16616.0] },
      { "customer":  55, "arrival_starting": [17013.0, 17013.0] },
      { "customer":  99, "arrival_starting": [17077.0, 17077.0] },
      { "customer":  25, "arrival_starting": [17165.0, 17165.0] },
      { "customer":  61, "arrival_starting": [17346.0, 17346.0] },
      { "customer":   4, "arrival_starting": [17652.0, 17652.0] },
      { "customer":  66, "arrival_starting": [17881.0, 17881.0] },
      { "customer":  39, "arrival_starting": [18209.0, 20362.0] },
      { "customer":  38, "arrival_starting": [20522.0, 20522.0] },
      { "customer":  52, "arrival_starting": [20761.0, 20861.0] },
      { "customer":  72, "arrival_starting": [21208.0, 21208.0] },
      { "customer":  84, "arrival_starting": [21296.0, 21296.0] },
      { "customer":  92, "arrival_starting": [21576.0, 21576.0] },
      { "customer":  10, "arrival_starting": [21630.0, 21707.0] },
      { "customer":  27, "arrival_starting": [22063.0, 22063.0] },
      { "customer":  90, "arrival_starting": [22127.0, 22127.0] },
      { "customer":  96, "arrival_starting": [22327.0, 22327.0] },
      { "customer":  75, "arrival_starting": [22488.0, 22488.0] },
      { "customer":   7, "arrival_starting": [22645.0, 22645.0] },
      { "customer":  28, "arrival_starting": [22745.0, 22745.0] },
      { "customer":  31, "arrival_starting": [22918.0, 23162.0] },
      { "customer":  97, "arrival_starting": [23400.0, 23400.0] },
      { "customer":  94, "arrival_starting": [23605.0, 23605.0] },
      { "customer":   0, "arrival_starting": [23701.0, 23701.0] }
    ]
  }
  ]

}

